{
  "operationName": "createSitting",
  "variables": {
    "command": {
      "name": "ApiSittingName[####]",
      "startDate": "[TIMENOW-yyyy-MM-dd]",
      "endDate": "[TIMENOW-yyyy-MM-dd]",
      "bodyReferences": [
        "EC_BODY_REFERENCE"
        ]
    }
  },
  "query": "mutation createSitting($command: CreateSittingCommandInput!) {  createSitting(command: $command) {  ...sitting  __typename  } }  fragment sitting on Sitting {  reference  name  startDate  endDate  bodies {  reference  shortName  name  __typename  }  createdBy  createdOn  updatedBy  updatedOn  __typename } "
}